jupyter_lab_progress/__init__.py
jupyter_lab_progress/_version.py
jupyter_lab_progress/display.py
jupyter_lab_progress/progress.py
jupyter_lab_progress/py.typed
jupyter_lab_progress/validator.py
jupyter_lab_progress-1.1.4.dist-info/licenses/LICENSE
jupyter_lab_progress-1.1.4.dist-info/METADATA
jupyter_lab_progress-1.1.4.dist-info/WHEEL
jupyter_lab_progress-1.1.4.dist-info/top_level.txt
jupyter_lab_progress-1.1.4.dist-info/RECORD
