Metadata-Version: 2.4
Name: jupyter-lab-progress
Version: 1.1.4
Summary: A comprehensive toolkit for creating interactive Jupyter notebook lab exercises with progress tracking, validation, and rich display utilities.
Author-email: Michael Lynn <michael.lynn@mongodb.com>
License: MIT
Project-URL: Homepage, https://github.com/mrlynn/jupyter-lab-utils
Project-URL: Documentation, https://github.com/mrlynn/jupyter-lab-utils#readme
Project-URL: Repository, https://github.com/mrlynn/jupyter-lab-utils.git
Project-URL: Bug Tracker, https://github.com/mrlynn/jupyter-lab-utils/issues
Project-URL: Changelog, https://github.com/mrlynn/jupyter-lab-utils/blob/main/CHANGELOG.md
Keywords: jupyter,notebook,education,lab,validation,progress,interactive,teaching,workshop,tutorial
Classifier: Development Status :: 5 - Production/Stable
Classifier: Intended Audience :: Education
Classifier: Intended Audience :: Developers
Classifier: License :: OSI Approved :: MIT License
Classifier: Operating System :: OS Independent
Classifier: Programming Language :: Python :: 3
Classifier: Programming Language :: Python :: 3.8
Classifier: Programming Language :: Python :: 3.9
Classifier: Programming Language :: Python :: 3.10
Classifier: Programming Language :: Python :: 3.11
Classifier: Programming Language :: Python :: 3.12
Classifier: Topic :: Education
Classifier: Topic :: Scientific/Engineering
Classifier: Topic :: Software Development :: Libraries :: Python Modules
Classifier: Framework :: Jupyter
Requires-Python: >=3.8
License-File: LICENSE
Requires-Dist: ipython>=7.0.0
Requires-Dist: pandas>=1.0.0
Requires-Dist: numpy>=1.18.0
Provides-Extra: dev
Requires-Dist: pytest>=7.0; extra == "dev"
Requires-Dist: pytest-cov>=4.0; extra == "dev"
Requires-Dist: black>=22.0; extra == "dev"
Requires-Dist: flake8>=5.0; extra == "dev"
Requires-Dist: mypy>=1.0; extra == "dev"
Requires-Dist: pre-commit>=2.20; extra == "dev"
Provides-Extra: docs
Requires-Dist: sphinx>=5.0; extra == "docs"
Requires-Dist: sphinx-rtd-theme>=1.0; extra == "docs"
Requires-Dist: myst-parser>=0.18; extra == "docs"
Dynamic: license-file
